chemify/__init__.py
chemify/main.py
chemify/version.py
chemify-0.0.4.dist-info/LICENSE.txt
chemify-0.0.4.dist-info/METADATA
chemify-0.0.4.dist-info/WHEEL
chemify-0.0.4.dist-info/top_level.txt
chemify-0.0.4.dist-info/RECORD
