Metadata-Version: 2.1
Name: chemify
Version: 0.0.4
Summary: Write any phrase as a list of chemical element symbols from the periodic table
Home-page: https://github.com/NGeorgescu/chemify
Author: NGeorgescu
Author-email: nsgeorgescu@gmail.com
License: see LICENSE.txt
Keywords: chemify periodic table element chemical symbol chemistry fun
Platform: UNKNOWN
